ruff_autoboat/__init__.py
ruff_autoboat/__main__.py
ruff_autoboat-0.14.14.data/scripts/ruff-autoboat
ruff_autoboat-0.14.14.dist-info/METADATA
ruff_autoboat-0.14.14.dist-info/WHEEL
ruff_autoboat-0.14.14.dist-info/licenses/LICENSE
ruff_autoboat-0.14.14.dist-info/RECORD
