Metadata-Version: 2.4
Name: ruff-autoboat
Version: 0.14.14
Classifier: Development Status :: 5 - Production/Stable
Classifier: Environment :: Console
Classifier: Intended Audience :: Developers
Classifier: License :: OSI Approved :: MIT License
Classifier: Operating System :: OS Independent
Classifier: Programming Language :: Python
Classifier: Programming Language :: Python :: 3.7
Classifier: Programming Language :: Python :: 3.8
Classifier: Programming Language :: Python :: 3.9
Classifier: Programming Language :: Python :: 3.10
Classifier: Programming Language :: Python :: 3.11
Classifier: Programming Language :: Python :: 3.12
Classifier: Programming Language :: Python :: 3.13
Classifier: Programming Language :: Python :: 3.14
Classifier: Programming Language :: Python :: 3 :: Only
Classifier: Programming Language :: Rust
Classifier: Topic :: Software Development :: Libraries :: Python Modules
Classifier: Topic :: Software Development :: Quality Assurance
License-File: LICENSE
Summary: An extremely fast Python linter and code formatter, written in Rust.
Keywords: automation,flake8,pycodestyle,pyflakes,pylint,clippy
Home-Page: https://docs.astral.sh/ruff
Author-email: "Astral Software Inc." <hey@astral.sh>
Requires-Python: >=3.7
Project-URL: Changelog, https://github.com/astral-sh/ruff/blob/main/CHANGELOG.md
Project-URL: Documentation, https://docs.astral.sh/ruff/
Project-URL: Repository, https://github.com/astral-sh/ruff
